setup.py
SpiderKeeper/__init__.py
SpiderKeeper/config.py
SpiderKeeper/job_redis_site.py
SpiderKeeper/run.py
SpiderKeeper/uwsgi.py
SpiderKeeper/app/__init__.py
SpiderKeeper/app/proxy/__init__.py
SpiderKeeper/app/proxy/spiderctrl.py
SpiderKeeper/app/proxy/contrib/__init__.py
SpiderKeeper/app/proxy/contrib/scrapy.py
SpiderKeeper/app/schedulers/__init__.py
SpiderKeeper/app/schedulers/common.py
SpiderKeeper/app/spider/__init__.py
SpiderKeeper/app/spider/controller.py
SpiderKeeper/app/spider/model.py
SpiderKeeper/app/util/__init__.py
SpiderKeeper/app/util/http.py
skcn.egg-info/PKG-INFO
skcn.egg-info/SOURCES.txt
skcn.egg-info/dependency_links.txt
skcn.egg-info/entry_points.txt
skcn.egg-info/requires.txt
skcn.egg-info/top_level.txt